curvesimilarities/__init__.py
curvesimilarities/dtw.py
curvesimilarities/frechet.py
curvesimilarities/integfrechet.py
curvesimilarities/util.py
curvesimilarities/_algorithms/__init__.py
curvesimilarities/_algorithms/dfd.py
curvesimilarities/_algorithms/dtw.py
curvesimilarities/_algorithms/fd.py
curvesimilarities/_algorithms/ifd.py
curvesimilarities-0.3.0.dist-info/LICENSE
curvesimilarities-0.3.0.dist-info/METADATA
curvesimilarities-0.3.0.dist-info/WHEEL
curvesimilarities-0.3.0.dist-info/top_level.txt
curvesimilarities-0.3.0.dist-info/RECORD
