Metadata-Version: 2.1
Name: curvesimilarities
Version: 0.3.0
Summary: Curve similarity measures
Author-email: Jisoo Song <jeesoo9595@snu.ac.kr>
License: Copyright 2024, Jisoo Song
Project-URL: homepage, https://github.com/JSS95/curvesimilarities
Project-URL: source, https://github.com/JSS95/curvesimilarities
Project-URL: documentation, https://curvesimilarities.readthedocs.io
Classifier: Development Status :: 4 - Beta
Classifier: Intended Audience :: Science/Research
Classifier: License :: OSI Approved :: BSD License
Classifier: Programming Language :: Python
Classifier: Programming Language :: Python :: 3
Classifier: Programming Language :: Python :: 3.9
Classifier: Programming Language :: Python :: 3.10
Classifier: Programming Language :: Python :: 3.11
Classifier: Programming Language :: Python :: 3.12
Classifier: Programming Language :: Python :: 3 :: Only
Classifier: Topic :: Scientific/Engineering
Classifier: Topic :: Scientific/Engineering :: Mathematics
Classifier: Operating System :: OS Independent
Requires-Python: >=3.9
License-File: LICENSE
Requires-Dist: numpy
Requires-Dist: scipy
Requires-Dist: numba
Provides-Extra: dev
Requires-Dist: flake8 ; extra == 'dev'
Requires-Dist: flake8-docstrings ; extra == 'dev'
Requires-Dist: black ; extra == 'dev'
Requires-Dist: isort ; extra == 'dev'
Requires-Dist: docformatter ; extra == 'dev'
Requires-Dist: doc8 ; extra == 'dev'
Requires-Dist: curvesimilarities[doc,test] ; extra == 'dev'
Provides-Extra: doc
Requires-Dist: sphinx ; extra == 'doc'
Requires-Dist: numpydoc ; extra == 'doc'
Requires-Dist: pydata-sphinx-theme ; extra == 'doc'
Requires-Dist: matplotlib ; extra == 'doc'
Provides-Extra: test
Requires-Dist: pytest ; extra == 'test'
